[{"period":"2019-01-01T00:00:00.000","consumption-for-eg-btu":135.74,"generation":14308.32,"consumption-for-eg-btu_pred":211.3705471257,"generation_pred":22660.9609123998},{"period":"2019-02-01T00:00:00.000","consumption-for-eg-btu":77.35,"generation":8818.93,"consumption-for-eg-btu_pred":187.4626221048,"generation_pred":20271.3047699041},{"period":"2019-03-01T00:00:00.000","consumption-for-eg-btu":81.59,"generation":9225.17,"consumption-for-eg-btu_pred":211.8813387161,"generation_pred":23328.8513740092},{"period":"2019-04-01T00:00:00.000","consumption-for-eg-btu":55.3,"generation":6699.21,"consumption-for-eg-btu_pred":142.9563358623,"generation_pred":15068.7994887731},{"period":"2019-05-01T00:00:00.000","consumption-for-eg-btu":79.33,"generation":8960.6,"consumption-for-eg-btu_pred":163.7574901126,"generation_pred":18715.1910422955},{"period":"2019-06-01T00:00:00.000","consumption-for-eg-btu":38.78,"generation":3665.96,"consumption-for-eg-btu_pred":148.5707748183,"generation_pred":17054.5667792205},{"period":"2019-07-01T00:00:00.000","consumption-for-eg-btu":149.64,"generation":18132.76,"consumption-for-eg-btu_pred":117.5583853028,"generation_pred":13268.1888863248},{"period":"2019-08-01T00:00:00.000","consumption-for-eg-btu":367.73,"generation":42217.23,"consumption-for-eg-btu_pred":217.5081404308,"generation_pred":23654.0883390127},{"period":"2019-09-01T00:00:00.000","consumption-for-eg-btu":144.79,"generation":16472.22,"consumption-for-eg-btu_pred":67.6142105723,"generation_pred":7610.3543010007},{"period":"2019-10-01T00:00:00.000","consumption-for-eg-btu":270.83,"generation":31190.54,"consumption-for-eg-btu_pred":188.8899660936,"generation_pred":20953.4292827864},{"period":"2019-11-01T00:00:00.000","consumption-for-eg-btu":172.5,"generation":19654.97,"consumption-for-eg-btu_pred":109.9465144242,"generation_pred":12314.6491873988},{"period":"2019-12-01T00:00:00.000","consumption-for-eg-btu":65.05,"generation":8531.89,"consumption-for-eg-btu_pred":126.7030643735,"generation_pred":14149.7527375833},{"period":"2020-01-01T00:00:00.000","consumption-for-eg-btu":203.65,"generation":24555.63,"consumption-for-eg-btu_pred":120.4280770377,"generation_pred":13852.9004995373},{"period":"2020-02-01T00:00:00.000","consumption-for-eg-btu":148.73,"generation":17470.86,"consumption-for-eg-btu_pred":233.5210144432,"generation_pred":24786.627086599},{"period":"2020-03-01T00:00:00.000","consumption-for-eg-btu":119.13,"generation":14165.53,"consumption-for-eg-btu_pred":184.8428588382,"generation_pred":19916.7938958423},{"period":"2020-04-01T00:00:00.000","consumption-for-eg-btu":60.01,"generation":7304.77,"consumption-for-eg-btu_pred":132.7362090903,"generation_pred":14680.0911847382},{"period":"2020-05-01T00:00:00.000","consumption-for-eg-btu":66.75,"generation":8122.35,"consumption-for-eg-btu_pred":139.9744454742,"generation_pred":15834.9730301303},{"period":"2020-06-01T00:00:00.000","consumption-for-eg-btu":66.79,"generation":7528.28,"consumption-for-eg-btu_pred":248.441370249,"generation_pred":26493.9407632187},{"period":"2020-07-01T00:00:00.000","consumption-for-eg-btu":78.6,"generation":9461.86,"consumption-for-eg-btu_pred":177.5750387795,"generation_pred":19674.5120103196},{"period":"2020-08-01T00:00:00.000","consumption-for-eg-btu":214.17,"generation":25828.91,"consumption-for-eg-btu_pred":201.2196230149,"generation_pred":21083.7906455551},{"period":"2020-09-01T00:00:00.000","consumption-for-eg-btu":185.88,"generation":21308.64,"consumption-for-eg-btu_pred":122.2312880323,"generation_pred":13519.2349066103},{"period":"2020-10-01T00:00:00.000","consumption-for-eg-btu":96.15,"generation":11026.34,"consumption-for-eg-btu_pred":194.5026453322,"generation_pred":21389.9906235875},{"period":"2020-11-01T00:00:00.000","consumption-for-eg-btu":55.52,"generation":6854.94,"consumption-for-eg-btu_pred":132.7290985515,"generation_pred":14411.645664721},{"period":"2020-12-01T00:00:00.000","consumption-for-eg-btu":142.0,"generation":17101.85,"consumption-for-eg-btu_pred":181.0808372264,"generation_pred":19915.1749798447},{"period":"2021-01-01T00:00:00.000","consumption-for-eg-btu":165.75,"generation":20226.23,"consumption-for-eg-btu_pred":149.5469523656,"generation_pred":15808.7754312269},{"period":"2021-02-01T00:00:00.000","consumption-for-eg-btu":0.0,"generation":0.0,"consumption-for-eg-btu_pred":151.9765316476,"generation_pred":16278.8401257952},{"period":"2021-03-01T00:00:00.000","consumption-for-eg-btu":84.77,"generation":9945.44,"consumption-for-eg-btu_pred":92.0234550406,"generation_pred":10305.7374195123},{"period":"2021-04-01T00:00:00.000","consumption-for-eg-btu":60.84,"generation":7370.02,"consumption-for-eg-btu_pred":170.7859656042,"generation_pred":17903.9714572811},{"period":"2021-05-01T00:00:00.000","consumption-for-eg-btu":142.19,"generation":16339.53,"consumption-for-eg-btu_pred":150.740450607,"generation_pred":16231.1188909462},{"period":"2021-06-01T00:00:00.000","consumption-for-eg-btu":198.97,"generation":23040.33,"consumption-for-eg-btu_pred":206.0176352121,"generation_pred":22087.0497444239},{"period":"2021-07-01T00:00:00.000","consumption-for-eg-btu":244.26,"generation":28125.68,"consumption-for-eg-btu_pred":189.9487843976,"generation_pred":20157.7310031005},{"period":"2021-08-01T00:00:00.000","consumption-for-eg-btu":169.57,"generation":19190.27,"consumption-for-eg-btu_pred":188.5979709333,"generation_pred":20812.9410329098},{"period":"2021-09-01T00:00:00.000","consumption-for-eg-btu":232.3,"generation":26451.81,"consumption-for-eg-btu_pred":198.0584516149,"generation_pred":21351.4898473994},{"period":"2021-10-01T00:00:00.000","consumption-for-eg-btu":161.06,"generation":19002.8,"consumption-for-eg-btu_pred":138.4267963908,"generation_pred":14996.139845776},{"period":"2021-11-01T00:00:00.000","consumption-for-eg-btu":188.2,"generation":22055.78,"consumption-for-eg-btu_pred":186.311052313,"generation_pred":20097.4974781631},{"period":"2021-12-01T00:00:00.000","consumption-for-eg-btu":67.86,"generation":6396.48,"consumption-for-eg-btu_pred":123.5201497879,"generation_pred":13022.4682787868},{"period":"2022-01-01T00:00:00.000","consumption-for-eg-btu":84.92,"generation":9336.28,"consumption-for-eg-btu_pred":178.5048558942,"generation_pred":19434.5684961385},{"period":"2022-02-01T00:00:00.000","consumption-for-eg-btu":154.48,"generation":17229.9,"consumption-for-eg-btu_pred":170.2749420695,"generation_pred":18250.6680635021},{"period":"2022-03-01T00:00:00.000","consumption-for-eg-btu":153.56,"generation":17285.05,"consumption-for-eg-btu_pred":170.6282753171,"generation_pred":17969.8286478967},{"period":"2022-04-01T00:00:00.000","consumption-for-eg-btu":57.91,"generation":6652.9,"consumption-for-eg-btu_pred":172.4409353298,"generation_pred":18683.4685952445},{"period":"2022-05-01T00:00:00.000","consumption-for-eg-btu":22.83,"generation":2745.48,"consumption-for-eg-btu_pred":155.7487474977,"generation_pred":16228.0922828661},{"period":"2022-06-01T00:00:00.000","consumption-for-eg-btu":120.05,"generation":13785.59,"consumption-for-eg-btu_pred":157.9929765664,"generation_pred":16972.6151245438},{"period":"2022-07-01T00:00:00.000","consumption-for-eg-btu":131.26,"generation":15194.56,"consumption-for-eg-btu_pred":160.7982514657,"generation_pred":17173.4610611756},{"period":"2022-08-01T00:00:00.000","consumption-for-eg-btu":206.93,"generation":24187.18,"consumption-for-eg-btu_pred":174.4234182521,"generation_pred":18526.4048495442},{"period":"2022-09-01T00:00:00.000","consumption-for-eg-btu":72.98,"generation":9332.46,"consumption-for-eg-btu_pred":191.8989164854,"generation_pred":20360.6152420668},{"period":"2022-10-01T00:00:00.000","consumption-for-eg-btu":136.91,"generation":16152.03,"consumption-for-eg-btu_pred":126.4158267418,"generation_pred":13612.1515562134},{"period":"2022-11-01T00:00:00.000","consumption-for-eg-btu":194.2,"generation":21402.33,"consumption-for-eg-btu_pred":142.4648614799,"generation_pred":15035.2727040159},{"period":"2022-12-01T00:00:00.000","consumption-for-eg-btu":183.83,"generation":20905.52,"consumption-for-eg-btu_pred":155.4937904146,"generation_pred":16958.7605753614}]